odoo/addons/base_report_auto_create_qweb/README.rst
odoo/addons/base_report_auto_create_qweb/__init__.py
odoo/addons/base_report_auto_create_qweb/__manifest__.py
odoo/addons/base_report_auto_create_qweb/i18n/am.po
odoo/addons/base_report_auto_create_qweb/i18n/ar.po
odoo/addons/base_report_auto_create_qweb/i18n/base_report_auto_create_qweb.pot
odoo/addons/base_report_auto_create_qweb/i18n/bg.po
odoo/addons/base_report_auto_create_qweb/i18n/bs.po
odoo/addons/base_report_auto_create_qweb/i18n/ca.po
odoo/addons/base_report_auto_create_qweb/i18n/ca_ES.po
odoo/addons/base_report_auto_create_qweb/i18n/cs.po
odoo/addons/base_report_auto_create_qweb/i18n/da.po
odoo/addons/base_report_auto_create_qweb/i18n/de.po
odoo/addons/base_report_auto_create_qweb/i18n/el_GR.po
odoo/addons/base_report_auto_create_qweb/i18n/en_AU.po
odoo/addons/base_report_auto_create_qweb/i18n/en_GB.po
odoo/addons/base_report_auto_create_qweb/i18n/es.po
odoo/addons/base_report_auto_create_qweb/i18n/es_AR.po
odoo/addons/base_report_auto_create_qweb/i18n/es_CL.po
odoo/addons/base_report_auto_create_qweb/i18n/es_CO.po
odoo/addons/base_report_auto_create_qweb/i18n/es_CR.po
odoo/addons/base_report_auto_create_qweb/i18n/es_DO.po
odoo/addons/base_report_auto_create_qweb/i18n/es_EC.po
odoo/addons/base_report_auto_create_qweb/i18n/es_ES.po
odoo/addons/base_report_auto_create_qweb/i18n/es_MX.po
odoo/addons/base_report_auto_create_qweb/i18n/es_PE.po
odoo/addons/base_report_auto_create_qweb/i18n/es_PY.po
odoo/addons/base_report_auto_create_qweb/i18n/es_VE.po
odoo/addons/base_report_auto_create_qweb/i18n/et.po
odoo/addons/base_report_auto_create_qweb/i18n/eu.po
odoo/addons/base_report_auto_create_qweb/i18n/fa.po
odoo/addons/base_report_auto_create_qweb/i18n/fi.po
odoo/addons/base_report_auto_create_qweb/i18n/fr.po
odoo/addons/base_report_auto_create_qweb/i18n/fr_CA.po
odoo/addons/base_report_auto_create_qweb/i18n/fr_CH.po
odoo/addons/base_report_auto_create_qweb/i18n/fr_FR.po
odoo14_addon_base_report_auto_create_qweb-14.0.1.0.1.dist-info/METADATA
odoo14_addon_base_report_auto_create_qweb-14.0.1.0.1.dist-info/WHEEL
odoo14_addon_base_report_auto_create_qweb-14.0.1.0.1.dist-info/top_level.txt
odoo14_addon_base_report_auto_create_qweb-14.0.1.0.1.dist-info/RECORD
