Metadata-Version: 2.1
Name: odoo14-addon-base-report-auto-create-qweb
Version: 14.0.1.0.1
Summary: Report qweb auto generation
Home-page: https://github.com/OCA/server-tools
Author: AvanzOSC, Tecnativa, Odoo Community Association (OCA)
Author-email: support@odoo-community.org
License: AGPL-3
Platform: UNKNOWN
Classifier: Programming Language :: Python
Classifier: Framework :: Odoo
Classifier: License :: OSI Approved :: GNU Affero General Public License v3
Requires-Python: >=3.6
Requires-Dist: odoo (<14.1dev,>=14.0a)
Requires-Dist: unidecode
